mxlogging/__init__.py
mxlogging/utils/__init__.py
mxlogging/utils/utils_varios.py
mxlogging-1.1.2.dist-info/LICENSE
mxlogging-1.1.2.dist-info/METADATA
mxlogging-1.1.2.dist-info/WHEEL
mxlogging-1.1.2.dist-info/top_level.txt
mxlogging-1.1.2.dist-info/RECORD
