Metadata-Version: 2.1
Name: mxlogging
Version: 1.1.2
Summary: Un sistema de logging optimizado para una interpretación clara y una integración sencilla de mensajes. Pensado para mejorar la trazabilidad y el diagnóstico en proyectos de software.
Home-page: https://github.com/Pistatxos/mxlogging
Author: Mario x
License: MIT
Classifier: Programming Language :: Python :: 3
Classifier: License :: OSI Approved :: MIT License
Classifier: Operating System :: OS Independent
Requires-Python: >=3.9
License-File: LICENSE
